[
    {
        "id" : 1,
        "name" : "Story Book",
        "title" : "Lorem ipsum dolor sit amet, consectetur adipisicing elit",
        "category" : "Free",
        "price" :"00" ,
        "img" : "https://img.freepik.com/free-vector/pop-up-book-with-outdoor-nature-scene_1308-100580.jpg?t=st=1734840168~exp=1734843768~hmac=a7d437edebc88f9dd026cb792f9ec7152634ae22cfbba3fb87b13c0bb7a6b43a&w=740"
    },

    {
        "id" : 2,
        "name" : "Comedy  Book",
        "title" : "Lorem ipsum dolor sit amet, consectetur adipisicing elit",
        "category" : "Free",
        "price" :"00" ,
         "img" : "https://img.freepik.com/free-vector/vertical-comic-cover-template-with-man-casino-games_52683-107368.jpg?t=st=1734840710~exp=1734844310~hmac=7b8f2bb21ef46a80f8eec3751857c494002cd1d1b81d9a9fed32a786ae3cb44e&w=740"   
        },
    
    {
        "id" : 3,
        "name" : "Sports Book",
        "title" : "Lorem ipsum dolor sit amet, consectetur adipisicing elit",
        "category" : "Sports",
        "price" :"50" ,
        "img" : "https://img.freepik.com/free-psd/gradient-sport-template-design_23-2149287760.jpg?t=st=1734840595~exp=1734844195~hmac=5c36bd9311040000ceec1fe7e0de91a7c14040567c73e68c1a37b5c048511cd7&w=740"
    },
    {
        "id" : 4,
        "name" : "Music Book",
        "title" : "Lorem ipsum dolor sit amet, consectetur adipisicing elit",
        "category" : "Songs",
        "price" :"100" ,
        "img" : "https://img.freepik.com/premium-psd/music-elements-book-with-vinyl-ukulele-guitar_23-2148355621.jpg?w=740"
    },
    {
        "id" : 5,
        "name" : "Science Book",
        "title" : "Lorem ipsum dolor sit amet, consectetur adipisicing elit",
        "category" : "Science",
        "price" :"70" ,
        "img" : "https://img.freepik.com/free-psd/science-class-print-template_23-2148990559.jpg?t=st=1734853781~exp=1734857381~hmac=c7f33bf703a6affbdd2f1a188718c6825dac9e4b56d91abdc0125a34db550943&w=740"
    },
    {
        "id" : 6,
        "name" : "History Book",
        "title" : "Lorem ipsum dolor sit amet, consectetur adipisicing elit",
        "category" : "History",
        "price" :"90" ,
        "img" : "https://img.freepik.com/free-vector/mexico-constitution-day-hand-drawn_23-2148794210.jpg?t=st=1734853944~exp=1734857544~hmac=80160aaed6c560bededd8e8c60ce1b46dc126c8289c4cc7f6755705ebd9d3b14&w=740"
    },
    {
        "id" : 7,
        "name" : "Art Book",
        "title" : "Lorem ipsum dolor sit amet, consectetur adipisicing elit",
        "category" : "Art",
        "price" :"80" ,
        "img" : "https://img.freepik.com/premium-photo/vector-book-cover-designs-various-themes_1252102-59778.jpg?w=740"
    },
    {
        "id" : 8,
        "name" : "Cooking Book",
        "title" : "Lorem ipsum dolor sit amet, consectetur adipisicing elit",
        "category" : "Cooking",
        "price" :"60" ,
        "img" : "https://img.freepik.com/free-psd/flat-design-gardening-template_23-2149329078.jpg?t=st=1734854149~exp=1734857749~hmac=8f31bf30edc5ba2e83abb5da361cf1dbca26840edfd7b2c65665e777355412b8&w=740"
    },
    {
        "id" : 9,
        "name" : "Travel Book",
        "title" : "Lorem ipsum dolor sit amet, consectetur adipisicing elit",
        "category" : "Travel",
        "price" :"40" ,
        "img" : "https://img.freepik.com/free-psd/banner-travel-template-design_23-2149207050.jpg?t=st=1734854037~exp=1734857637~hmac=711b8abfd068fa4101da67108140cc0f5dc0bc0c959686ba0fa85afb7c120715&w=826"
    },
    {
        "id" : 10,
        "name" : "Fashion Book",
        "title" : "Lorem ipsum dolor sit amet, consectetur adipisicing elit",
        "category" : "Fashion",
        "price" :"30" ,
        "img" : "https://img.freepik.com/free-vector/flat-design-minimal-boutique-poster-template_23-2149337456.jpg?t=st=1734854172~exp=1734857772~hmac=a5ab1f737b0846f1b42fcac8d842800d8170f1acf26a55e48af27e18bc093549&w=740"
    },{
        "id" : 11,
        "name" : "Story Book",
        "title" : "Lorem ipsum dolor sit amet, consectetur adipisicing elit",
        "category" : "Free",
        "price" :"00" ,
        "img" : "https://img.freepik.com/free-vector/open-book-with-forest-scene_1308-171719.jpg?t=st=1734848523~exp=1734852123~hmac=fa14048c4e0ae037aba37dd3b6c65007c17c61576ec3efc8dadfaf1852fdcbf3&w=740"

    }
        
    


]        